README.txt
setup.py
restler/__init__.py
restler/_version.py
restler/datetime_safe.py
restler/decorators.py
restler/models.py
restler/serializers.py
restler_serialization.egg-info/PKG-INFO
restler_serialization.egg-info/SOURCES.txt
restler_serialization.egg-info/dependency_links.txt
restler_serialization.egg-info/top_level.txt