Metadata-Version: 1.1
Name: restler-serialization
Version: 0.4.1
Summary: Restler provides flexible and configurable JSON and XML object serialization for the web
Home-page: https://bitbucket.org/curtis/restler
Author: Curtis Thompson
Author-email: curtis.thompson@gmail.com
License: MIT
Keywords: serialization json xml
Platform: UNKNOWN
Classifier: Development Status :: 4 - Beta
Classifier: Environment :: Web Environment
Classifier: Intended Audience :: Developers
Classifier: Topic :: Internet :: WWW/HTTP
Classifier: Topic :: Software Development :: Object Brokering
Classifier: Topic :: Utilities
